MANIFEST.in
README.txt
setup.py
collective/__init__.py
collective.dancingcustomtemplates.egg-info/PKG-INFO
collective.dancingcustomtemplates.egg-info/SOURCES.txt
collective.dancingcustomtemplates.egg-info/dependency_links.txt
collective.dancingcustomtemplates.egg-info/entry_points.txt
collective.dancingcustomtemplates.egg-info/namespace_packages.txt
collective.dancingcustomtemplates.egg-info/not-zip-safe
collective.dancingcustomtemplates.egg-info/requires.txt
collective.dancingcustomtemplates.egg-info/top_level.txt
collective/dancingcustomtemplates/__init__.py
collective/dancingcustomtemplates/configure.zcml
collective/dancingcustomtemplates/monkey.py
collective/dancingcustomtemplates/browser/__init__.py
collective/dancingcustomtemplates/browser/configure.zcml
collective/dancingcustomtemplates/browser/interfaces.py
collective/dancingcustomtemplates/browser/subscribe.py
collective/dancingcustomtemplates/profiles/default/browserlayer.xml
collective/dancingcustomtemplates/profiles/default/metadata.xml
docs/HISTORY.txt
docs/LICENSE.GPL
docs/LICENSE.txt