Metadata-Version: 1.1
Name: collective.dancingcustomtemplates
Version: 1.0.0
Summary: A product that customize some templates for S&D
Home-page: http://plone.org/products/collective.dancingcustomtemplates
Author: RedTurtle
Author-email: sviluppoplone@redturtle.it
License: gpl
Keywords: newsletter custom singing dancing
Platform: UNKNOWN
Classifier: Programming Language :: Python
Classifier: Framework :: Plone
Classifier: Framework :: Plone :: 3.3
Classifier: Framework :: Plone :: 4.0
Classifier: Framework :: Plone :: 4.2
Classifier: Topic :: Software Development :: Libraries :: Python Modules
